svgsitemap
