Metadata-Version: 1.0
Name: svgsitemap
Version: 0.1.1
Summary: a site map using PyGraphviz and svg
Home-page: http://k0s.org/map.svg
Author: Jeff Hammel
Author-email: jhammel@mozilla.com
License: MPL
Platform: UNKNOWN
